ccv_generator/__init__.py
ccv_generator/cli.py
ccv_generator/downloader.py
ccv_generator/generator.py
ccv_generator-0.1.1.dist-info/licenses/LICENSE
ccv_generator-0.1.1.dist-info/METADATA
ccv_generator-0.1.1.dist-info/WHEEL
ccv_generator-0.1.1.dist-info/entry_points.txt
ccv_generator-0.1.1.dist-info/top_level.txt
ccv_generator-0.1.1.dist-info/RECORD
