Metadata-Version: 2.4
Name: ccv_generator
Version: 0.1.1
Summary: Command line tool and library to parse and generate Canadian Common CV (CCV) files
Author: Damien Masson
License: MIT
License-File: LICENSE
Requires-Dist: platformdirs==4.3.6
Requires-Dist: Requests==2.32.3
Requires-Dist: ruamel.base==1.0.0
Dynamic: license-file
